pytest_caprng
